nullsmtpd/__init__.py
nullsmtpd/logger.py
nullsmtpd/nullsmtpd.py
nullsmtpd/version.py
nullsmtpd-0.5.1.dist-info/LICENSE.rst
nullsmtpd-0.5.1.dist-info/METADATA
nullsmtpd-0.5.1.dist-info/WHEEL
nullsmtpd-0.5.1.dist-info/entry_points.txt
nullsmtpd-0.5.1.dist-info/top_level.txt
nullsmtpd-0.5.1.dist-info/RECORD
