Metadata-Version: 2.1
Name: nullsmtpd
Version: 0.5.1
Summary: Fake SMTP server
Home-page: http://github.com/MasterOdin/nullsmtpd
Author: Matthew Peveler
Author-email: matt.peveler@gmail.com
License: UNKNOWN
Platform: UNKNOWN
Classifier: Development Status :: 5 - Production/Stable
Classifier: Programming Language :: Python
Classifier: Programming Language :: Python :: 3 :: Only
Classifier: Programming Language :: Python :: 3.5
Classifier: Programming Language :: Python :: 3.6
Classifier: Environment :: Console
Classifier: Framework :: AsyncIO
Classifier: Intended Audience :: Developers
Classifier: Intended Audience :: Information Technology
Classifier: License :: Public Domain
Classifier: Topic :: Communications :: Email :: Mail Transport Agents
Requires-Python: >=3.5.x
Requires-Dist: aiosmtpd (<=1.3)
